{
  "targets": {
    "swap": {}
  },
  "passes": [
    {
      "vertex_shader": "minecraft:core/screenquad",
      "fragment_shader": "substancecraft:post/shader_effects",
      "inputs": [
        {
          "sampler_name": "In",
          "target": "minecraft:main",
          "bilinear": true
        }
      ],
      "output": "swap",
      "uniforms": {
        "Config": [
          {
            "name": "colorEnhancementEnabled",
            "type": "int",
            "value": 0
          },
          {
            "name": "colorResolutionEnabled",
            "type": "int",
            "value": 0
          },
          {
            "name": "dynamicColorEnabled",
            "type": "int",
            "value": 0
          },
          {
            "name": "mosaicEnabled",
            "type": "int",
            "value": 0
          },
          {
            "name": "saturation",
            "type": "float",
            "value": 1.0
          },
          {
            "name": "resolution",
            "type": "float",
            "value": 1.0
          },
          {
            "name": "time",
            "type": "float",
            "value": 1.0
          },
          {
            "name": "hueIntensity",
            "type": "float",
            "value": 1.0
          },
          {
            "name": "mosaicSize",
            "type": "float",
            "value": 1.0
          }
        ]
      }
    },
    {
      "vertex_shader": "minecraft:core/screenquad",
      "fragment_shader": "minecraft:post/blit",
      "inputs": [
        {
          "sampler_name": "In",
          "target": "swap"
        }
      ],
      "uniforms": {
        "BlitConfig": [
          {
            "name": "ColorModulate",
            "type": "vec4",
            "value": [ 1.0, 1.0, 1.0, 1.0 ]
          }
        ]
      },
      "output": "minecraft:main"
    }
  ]
}